Metadata-Version: 2.1
Name: prawhat
Version: 0.0.2
Summary: A simple library to whatsapp
Home-page: UNKNOWN
Author: Pratham Chugh
Author-email: pratham12082005@gmail.com
License: MIT
Keywords: whatsapp
Platform: UNKNOWN
Classifier: Development Status :: 5 - Production/Stable
Classifier: Intended Audience :: Education
Classifier: Operating System :: Microsoft :: Windows :: Windows 10
Classifier: License :: OSI Approved :: MIT License
Classifier: Programming Language :: Python :: 3
License-File: LICENCE.txt
